deep_research_py/__init__.py
deep_research_py/deep_research.py
deep_research_py/feedback.py
deep_research_py/prompt.py
deep_research_py/run.py
deep_research_py/ai/__init__.py
deep_research_py/ai/providers.py
deep_research_py/ai/text_splitter.py
deep_research_py-0.1.2.dist-info/METADATA
deep_research_py-0.1.2.dist-info/WHEEL
deep_research_py-0.1.2.dist-info/entry_points.txt
deep_research_py-0.1.2.dist-info/RECORD
