Metadata-Version: 2.4
Name: deep-research-py
Version: 0.1.2
Summary: An AI-powered deep research assistant in python
Author-email: Esteban Puerta <epuer94@gmail.com>
License: MIT
Requires-Python: >=3.9
Requires-Dist: aiofiles>=23.2.1
Requires-Dist: aiohttp>=3.9.0
Requires-Dist: firecrawl-py>=1.11.1
Requires-Dist: openai>=1.0.0
Requires-Dist: prompt-toolkit>=3.0.0
Requires-Dist: python-dotenv>=1.0.0
Requires-Dist: rich>=13.7.0
Requires-Dist: tiktoken>=0.5.0
Requires-Dist: typer[all]>=0.9.0
Provides-Extra: dev
Requires-Dist: black>=23.7.0; extra == 'dev'
Requires-Dist: firecrawl-py; extra == 'dev'
Requires-Dist: isort>=5.12.0; extra == 'dev'
Requires-Dist: mypy>=1.5.0; extra == 'dev'
Requires-Dist: pytest-asyncio>=0.21.0; extra == 'dev'
Requires-Dist: pytest>=7.4.0; extra == 'dev'
